nmicheck/__init__.py
nmicheck/check.py
nmicheck/participant.py
nmicheck/tools.py
nmicheck/version.py
nmicheck-0.3.0.dist-info/licenses/LICENSE
nmicheck-0.3.0.dist-info/WHEEL
nmicheck-0.3.0.dist-info/METADATA
nmicheck-0.3.0.dist-info/RECORD
