Metadata-Version: 2.4
Name: nmicheck
Version: 0.3.0
Summary: Functions to validate National Metering Identifiers (NMIs)
Author-email: Alex Guinman <alex@guinman.id.au>
Requires-Python: >=3.10
Classifier: License :: OSI Approved :: MIT License
Classifier: Programming Language :: Python :: 3
Classifier: Programming Language :: Python :: 3.13
Classifier: Programming Language :: Python :: 3.12
Classifier: Programming Language :: Python :: 3.11
Classifier: Programming Language :: Python :: 3.10
Classifier: Operating System :: OS Independent
License-File: LICENSE
Requires-Dist: ruff ; extra == "test"
Requires-Dist: pytest >=2.7.3 ; extra == "test"
Requires-Dist: pytest-cov ; extra == "test"
Requires-Dist: mypy ; extra == "test"
Project-URL: Source, https://github.com/aguinane/NMI-Checksum/
Provides-Extra: test
